pywph/__init__.py
pywph/filters.py
pywph/utils.py
pywph/wph.py
pywph/wph_operator.py
pywph-1.1.2.dist-info/LICENSE.md
pywph-1.1.2.dist-info/METADATA
pywph-1.1.2.dist-info/WHEEL
pywph-1.1.2.dist-info/top_level.txt
pywph-1.1.2.dist-info/RECORD
