Metadata-Version: 2.1
Name: pywph
Version: 1.1.2
Summary: Wavelet Phase Harmonics in Python with GPU acceleration.
Home-page: https://github.com/bregaldo/pywph
Author: Bruno Régaldo-Saint Blancard
Author-email: bregaldosaintblancard@flatironinstitute.org
Classifier: Programming Language :: Python :: 3
Classifier: License :: OSI Approved :: BSD License
Classifier: Operating System :: OS Independent
Requires-Python: >=3.8
License-File: LICENSE.md
